git_pw/__init__.py
git_pw/api.py
git_pw/bundle.py
git_pw/config.py
git_pw/logger.py
git_pw/patch.py
git_pw/series.py
git_pw/shell.py
git_pw/utils.py
git_pw-2.7.1.dist-info/LICENSE
git_pw-2.7.1.dist-info/METADATA
git_pw-2.7.1.dist-info/WHEEL
git_pw-2.7.1.dist-info/entry_points.txt
git_pw-2.7.1.dist-info/pbr.json
git_pw-2.7.1.dist-info/top_level.txt
git_pw-2.7.1.dist-info/RECORD
