Metadata-Version: 2.2
Name: git-pw
Version: 2.7.1
Summary: Git-Patchwork integration tool
Home-page: https://github.com/getpatchwork/git-pw
Author: Stephen Finucane
Author-email: stephen@that.guru
License: MIT License
Project-URL: Bug Tracker, https://github.com/getpatchwork/git-pw/issues
Project-URL: Source Code, https://github.com/getpatchwork/git-pw
Project-URL: Documentation, https://git-pw.readthedocs.io
Keywords: git patchwork
Classifier: Development Status :: 5 - Production/Stable
Classifier: Environment :: Console
Classifier: Intended Audience :: Developers
Classifier: Intended Audience :: Information Technology
Classifier: Programming Language :: Python :: 3
Classifier: Programming Language :: Python :: 3 :: Only
Classifier: Programming Language :: Python
Classifier: License :: OSI Approved :: MIT License
Classifier: Operating System :: OS Independent
Requires-Python: >=3.9
License-File: LICENSE
Requires-Dist: click>=6.0
Requires-Dist: requests>=2.0
Requires-Dist: tabulate>=0.8
Requires-Dist: arrow>=0.10
Requires-Dist: PyYAML>=5.1
Dynamic: author
Dynamic: author-email
Dynamic: keywords
Dynamic: license
Dynamic: project-url
Dynamic: requires-dist
Dynamic: requires-python
Dynamic: summary
